{
  "date": "2023-02-02T19:05:32.143Z",
  "coordinates": [
    24.43,
    54.64
  ],
  "label": "Abu Dhabi",
  "full_label": "389, Ad Diyafah Street, Zayed International Airport, Abu Dhabi, Abu Dhabi Emirate, 23500, United Arab Emirates",
  "timezone": {
    "name": "Asia/Dubai",
    "countries": [
      "AE",
      "OM",
      "RE",
      "SC",
      "TF"
    ],
    "utcOffset": 240,
    "utcOffsetStr": "+04:00",
    "dstOffset": 240,
    "dstOffsetStr": "+04:00",
    "aliasOf": null
  },
  "country_code": "ae",
  "country_emoji": "🇦🇪"
}
